[
 {
   "contract_id": 251,
   "investor_id": 13,
   "date_init": "2018-05-16",
   "date_expired": "2019-05-16",
   "amount": 500000,
   "initial_amount": 500000,
   "created_at": "2019-01-07 00:00:00",
   "updated_at": "2019-01-07 00:00:00",
   "status": 1,
   "created_by": 1
 },
 {
   "contract_id": 251,
   "investor_id": 13,
   "date_init": "2018-05-17",
   "date_expired": "2019-05-16",
   "amount": 500000,
   "initial_amount": 500000,
   "created_at": "2019-01-07 00:00:00",
   "updated_at": "2019-01-07 00:00:00",
   "status": 1,
   "created_by": 1
 },
 {
   "contract_id": 251,
   "investor_id": 13,
   "date_init": "2018-04-03",
   "date_expired": "2019-04-03",
   "amount": 6540000,
   "initial_amount": 6540000,
   "created_at": "2019-01-07 00:00:00",
   "updated_at": "2019-01-07 00:00:00",
   "status": 1,
   "created_by": 1
 },
 {
   "contract_id": 205,
   "investor_id": 18,
   "date_init": "2018-08-19",
   "date_expired": "2019-08-19",
   "amount": 2500000,
   "initial_amount": 2500000,
   "created_at": "2019-01-07 00:00:00",
   "updated_at": "2019-01-07 00:00:00",
   "status": 1,
   "created_by": 1
 },
 {
   "contract_id": 205,
   "investor_id": 18,
   "date_init": "2018-03-19",
   "date_expired": "2019-03-19",
   "amount": 3000000,
   "initial_amount": 3000000,
   "created_at": "2019-01-07 00:00:00",
   "updated_at": "2019-01-07 00:00:00",
   "status": 1,
   "created_by": 1
 },
 {
   "contract_id": 206,
   "investor_id": 18,
   "date_init": "2018-08-19",
   "date_expired": "2019-08-19",
   "amount": 1440000,
   "initial_amount": 1440000,
   "created_at": "2019-01-07 00:00:00",
   "updated_at": "2019-01-07 00:00:00",
   "status": 1,
   "created_by": 1
 },
 {
   "contract_id": 206,
   "investor_id": 18,
   "date_init": "2018-08-24",
   "date_expired": "2019-08-20",
   "amount": 460000,
   "initial_amount": 460000,
   "created_at": "2019-01-07 00:00:00",
   "updated_at": "2019-01-07 00:00:00",
   "status": 1,
   "created_by": 1
 },
 {
   "contract_id": 207,
   "investor_id": 41,
   "date_init": "2018-06-23",
   "date_expired": "2019-06-23",
   "amount": 1650000,
   "initial_amount": 1650000,
   "created_at": "2019-01-07 00:00:00",
   "updated_at": "2019-01-07 00:00:00",
   "status": 1,
   "created_by": 1
 },
 {
   "contract_id": 207,
   "investor_id": 41,
   "date_init": "2018-11-30",
   "date_expired": "2019-11-30",
   "amount": 400000,
   "initial_amount": 400000,
   "created_at": "2019-01-07 00:00:00",
   "updated_at": "2019-01-07 00:00:00",
   "status": 1,
   "created_by": 1
 },
 {
   "contract_id": 207,
   "investor_id": 41,
   "date_init": "2018-12-14",
   "date_expired": "2019-12-14",
   "amount": 900000,
   "initial_amount": 900000,
   "created_at": "2019-01-07 00:00:00",
   "updated_at": "2019-01-07 00:00:00",
   "status": 1,
   "created_by": 1
 },
 {
   "contract_id": 207,
   "investor_id": 41,
   "date_init": "2018-02-01",
   "date_expired": "2019-02-01",
   "amount": 500000,
   "initial_amount": 500000,
   "created_at": "2019-01-07 00:00:00",
   "updated_at": "2019-01-07 00:00:00",
   "status": 1,
   "created_by": 1
 },
 {
   "contract_id": 208,
   "investor_id": 170,
   "date_init": "2018-08-14",
   "date_expired": "2019-08-14",
   "amount": 4250000,
   "initial_amount": 4250000,
   "created_at": "2019-01-07 00:00:00",
   "updated_at": "2019-01-07 00:00:00",
   "status": 1,
   "created_by": 1
 },
 {
   "contract_id": 209,
   "investor_id": 43,
   "date_init": "2018-12-04",
   "date_expired": "2019-12-04",
   "amount": 2500000,
   "initial_amount": 2500000,
   "created_at": "2019-01-07 00:00:00",
   "updated_at": "2019-01-07 00:00:00",
   "status": 1,
   "created_by": 1
 },
 {
   "contract_id": 209,
   "investor_id": 43,
   "date_init": "2018-12-18",
   "date_expired": "2019-12-18",
   "amount": 2500000,
   "initial_amount": 2500000,
   "created_at": "2019-01-07 00:00:00",
   "updated_at": "2019-01-07 00:00:00",
   "status": 1,
   "created_by": 1
 },
 {
   "contract_id": 209,
   "investor_id": 43,
   "date_init": "2018-01-31",
   "date_expired": "2019-01-31",
   "amount": 5000000,
   "initial_amount": 5000000,
   "created_at": "2019-01-07 00:00:00",
   "updated_at": "2019-01-07 00:00:00",
   "status": 1,
   "created_by": 1
 },
 {
   "contract_id": 209,
   "investor_id": 43,
   "date_init": "2018-02-28",
   "date_expired": "2019-02-28",
   "amount": 5000000,
   "initial_amount": 5000000,
   "created_at": "2019-01-07 00:00:00",
   "updated_at": "2019-01-07 00:00:00",
   "status": 1,
   "created_by": 1
 },
 {
   "contract_id": 209,
   "investor_id": 43,
   "date_init": "2018-03-31",
   "date_expired": "2019-03-31",
   "amount": 5000000,
   "initial_amount": 5000000,
   "created_at": "2019-01-07 00:00:00",
   "updated_at": "2019-01-07 00:00:00",
   "status": 1,
   "created_by": 1
 },
 {
   "contract_id": 209,
   "investor_id": 43,
   "date_init": "2018-04-07",
   "date_expired": "2019-04-07",
   "amount": 2500000,
   "initial_amount": 2500000,
   "created_at": "2019-01-07 00:00:00",
   "updated_at": "2019-01-07 00:00:00",
   "status": 1,
   "created_by": 1
 },
 {
   "contract_id": 209,
   "investor_id": 43,
   "date_init": "2018-04-30",
   "date_expired": "2019-04-30",
   "amount": 5000000,
   "initial_amount": 5000000,
   "created_at": "2019-01-07 00:00:00",
   "updated_at": "2019-01-07 00:00:00",
   "status": 1,
   "created_by": 1
 },
 {
   "contract_id": 209,
   "investor_id": 43,
   "date_init": "2018-05-30",
   "date_expired": "2019-05-30",
   "amount": 5000000,
   "initial_amount": 5000000,
   "created_at": "2019-01-07 00:00:00",
   "updated_at": "2019-01-07 00:00:00",
   "status": 1,
   "created_by": 1
 },
 {
   "contract_id": 210,
   "investor_id": 44,
   "date_init": "2018-09-29",
   "date_expired": "2019-03-29",
   "amount": 10000000,
   "initial_amount": 10000000,
   "created_at": "2019-01-07 00:00:00",
   "updated_at": "2019-01-07 00:00:00",
   "status": 1,
   "created_by": 1
 },
 {
   "contract_id": 211,
   "investor_id": 45,
   "date_init": "2018-12-02",
   "date_expired": "2019-12-02",
   "amount": 1000000,
   "initial_amount": 1000000,
   "created_at": "2019-01-07 00:00:00",
   "updated_at": "2019-01-07 00:00:00",
   "status": 1,
   "created_by": 1
 },
 {
   "contract_id": 211,
   "investor_id": 45,
   "date_init": "2018-09-06",
   "date_expired": "2019-09-06",
   "amount": 1000000,
   "initial_amount": 1000000,
   "created_at": "2019-01-07 00:00:00",
   "updated_at": "2019-01-07 00:00:00",
   "status": 1,
   "created_by": 1
 },
 {
   "contract_id": 212,
   "investor_id": 46,
   "date_init": "2018-12-08",
   "date_expired": "2019-12-08",
   "amount": 300000,
   "initial_amount": 300000,
   "created_at": "2019-01-07 00:00:00",
   "updated_at": "2019-01-07 00:00:00",
   "status": 1,
   "created_by": 1
 },
 {
   "contract_id": 212,
   "investor_id": 46,
   "date_init": "2018-03-03",
   "date_expired": "2019-03-03",
   "amount": 500000,
   "initial_amount": 500000,
   "created_at": "2019-01-07 00:00:00",
   "updated_at": "2019-01-07 00:00:00",
   "status": 1,
   "created_by": 1
 },
 {
   "contract_id": 213,
   "investor_id": 47,
   "date_init": "2018-10-21",
   "date_expired": "2019-10-21",
   "amount": 270000,
   "initial_amount": 270000,
   "created_at": "2019-01-07 00:00:00",
   "updated_at": "2019-01-07 00:00:00",
   "status": 1,
   "created_by": 1
 },
 {
   "contract_id": 213,
   "investor_id": 47,
   "date_init": "2018-11-24",
   "date_expired": "2019-11-24",
   "amount": 270000,
   "initial_amount": 270000,
   "created_at": "2019-01-07 00:00:00",
   "updated_at": "2019-01-07 00:00:00",
   "status": 1,
   "created_by": 1
 },
 {
   "contract_id": 213,
   "investor_id": 47,
   "date_init": "2018-12-20",
   "date_expired": "2019-12-20",
   "amount": 290000,
   "initial_amount": 290000,
   "created_at": "2019-01-07 00:00:00",
   "updated_at": "2019-01-07 00:00:00",
   "status": 1,
   "created_by": 1
 },
 {
   "contract_id": 213,
   "investor_id": 47,
   "date_init": "2018-01-27",
   "date_expired": "2019-01-27",
   "amount": 280000,
   "initial_amount": 280000,
   "created_at": "2019-01-07 00:00:00",
   "updated_at": "2019-01-07 00:00:00",
   "status": 1,
   "created_by": 1
 },
 {
   "contract_id": 213,
   "investor_id": 47,
   "date_init": "2018-02-28",
   "date_expired": "2019-02-28",
   "amount": 300000,
   "initial_amount": 300000,
   "created_at": "2019-01-07 00:00:00",
   "updated_at": "2019-01-07 00:00:00",
   "status": 1,
   "created_by": 1
 },
 {
   "contract_id": 213,
   "investor_id": 47,
   "date_init": "2018-03-28",
   "date_expired": "2019-03-28",
   "amount": 270000,
   "initial_amount": 270000,
   "created_at": "2019-01-07 00:00:00",
   "updated_at": "2019-01-07 00:00:00",
   "status": 1,
   "created_by": 1
 },
 {
   "contract_id": 213,
   "investor_id": 47,
   "date_init": "2018-04-28",
   "date_expired": "2019-04-28",
   "amount": 260000,
   "initial_amount": 260000,
   "created_at": "2019-01-07 00:00:00",
   "updated_at": "2019-01-07 00:00:00",
   "status": 1,
   "created_by": 1
 },
 {
   "contract_id": 213,
   "investor_id": 47,
   "date_init": "2018-05-25",
   "date_expired": "2019-05-25",
   "amount": 310000,
   "initial_amount": 310000,
   "created_at": "2019-01-07 00:00:00",
   "updated_at": "2019-01-07 00:00:00",
   "status": 1,
   "created_by": 1
 },
 {
   "contract_id": 213,
   "investor_id": 47,
   "date_init": "2018-06-20",
   "date_expired": "2019-06-20",
   "amount": 320000,
   "initial_amount": 320000,
   "created_at": "2019-01-07 00:00:00",
   "updated_at": "2019-01-07 00:00:00",
   "status": 1,
   "created_by": 1
 },
 {
   "contract_id": 213,
   "investor_id": 47,
   "date_init": "2018-07-22",
   "date_expired": "2019-07-22",
   "amount": 300000,
   "initial_amount": 300000,
   "created_at": "2019-01-07 00:00:00",
   "updated_at": "2019-01-07 00:00:00",
   "status": 1,
   "created_by": 1
 },
 {
   "contract_id": 213,
   "investor_id": 47,
   "date_init": "2018-08-22",
   "date_expired": "2019-08-22",
   "amount": 320000,
   "initial_amount": 320000,
   "created_at": "2019-01-07 00:00:00",
   "updated_at": "2019-01-07 00:00:00",
   "status": 1,
   "created_by": 1
 },
 {
   "contract_id": 213,
   "investor_id": 47,
   "date_init": "2018-11-26",
   "date_expired": "2019-11-26",
   "amount": 370000,
   "initial_amount": 370000,
   "created_at": "2019-01-07 00:00:00",
   "updated_at": "2019-01-07 00:00:00",
   "status": 1,
   "created_by": 1
 },
 {
   "contract_id": 214,
   "investor_id": 48,
   "date_init": "2018-11-26",
   "date_expired": "2019-11-26",
   "amount": 1500000,
   "initial_amount": 1500000,
   "created_at": "2019-01-07 00:00:00",
   "updated_at": "2019-01-07 00:00:00",
   "status": 1,
   "created_by": 1
 },
 {
   "contract_id": 214,
   "investor_id": 48,
   "date_init": "2018-04-07",
   "date_expired": "2019-04-07",
   "amount": 1000000,
   "initial_amount": 1000000,
   "created_at": "2019-01-07 00:00:00",
   "updated_at": "2019-01-07 00:00:00",
   "status": 1,
   "created_by": 1
 },
 {
   "contract_id": 215,
   "investor_id": 49,
   "date_init": "2018-12-09",
   "date_expired": "2019-12-09",
   "amount": 2450000,
   "initial_amount": 2450000,
   "created_at": "2019-01-07 00:00:00",
   "updated_at": "2019-01-07 00:00:00",
   "status": 1,
   "created_by": 1
 },
 {
   "contract_id": 215,
   "investor_id": 49,
   "date_init": "2018-12-16",
   "date_expired": "2019-12-16",
   "amount": 135000,
   "initial_amount": 135000,
   "created_at": "2019-01-07 00:00:00",
   "updated_at": "2019-01-07 00:00:00",
   "status": 1,
   "created_by": 1
 },
 {
   "contract_id": 216,
   "investor_id": 50,
   "date_init": "2018-08-22",
   "date_expired": "2019-08-22",
   "amount": 1000000,
   "initial_amount": 1000000,
   "created_at": "2019-01-07 00:00:00",
   "updated_at": "2019-01-07 00:00:00",
   "status": 1,
   "created_by": 1
 },
 {
   "contract_id": 216,
   "investor_id": 50,
   "date_init": "2018-08-28",
   "date_expired": "2019-08-28",
   "amount": 1000000,
   "initial_amount": 1000000,
   "created_at": "2019-01-07 00:00:00",
   "updated_at": "2019-01-07 00:00:00",
   "status": 1,
   "created_by": 1
 },
 {
   "contract_id": 216,
   "investor_id": 50,
   "date_init": "2018-02-12",
   "date_expired": "2019-02-12",
   "amount": 1000000,
   "initial_amount": 1000000,
   "created_at": "2019-01-07 00:00:00",
   "updated_at": "2019-01-07 00:00:00",
   "status": 1,
   "created_by": 1
 },
 {
   "contract_id": 216,
   "investor_id": 50,
   "date_init": "2018-03-09",
   "date_expired": "2019-03-09",
   "amount": 500000,
   "initial_amount": 500000,
   "created_at": "2019-01-07 00:00:00",
   "updated_at": "2019-01-07 00:00:00",
   "status": 1,
   "created_by": 1
 },
 {
   "contract_id": 216,
   "investor_id": 50,
   "date_init": "2018-04-05",
   "date_expired": "2019-04-05",
   "amount": 3000000,
   "initial_amount": 3000000,
   "created_at": "2019-01-07 00:00:00",
   "updated_at": "2019-01-07 00:00:00",
   "status": 1,
   "created_by": 1
 },
 {
   "contract_id": 216,
   "investor_id": 50,
   "date_init": "2018-05-24",
   "date_expired": "2019-05-24",
   "amount": 500000,
   "initial_amount": 500000,
   "created_at": "2019-01-07 00:00:00",
   "updated_at": "2019-01-07 00:00:00",
   "status": 1,
   "created_by": 1
 },
 {
   "contract_id": 217,
   "investor_id": 52,
   "date_init": "2018-12-13",
   "date_expired": "2019-12-13",
   "amount": 1000000,
   "initial_amount": 1000000,
   "created_at": "2019-01-07 00:00:00",
   "updated_at": "2019-01-07 00:00:00",
   "status": 1,
   "created_by": 1
 },
 {
   "contract_id": 217,
   "investor_id": 52,
   "date_init": "2018-02-09",
   "date_expired": "2019-02-09",
   "amount": 1000000,
   "initial_amount": 1000000,
   "created_at": "2019-01-07 00:00:00",
   "updated_at": "2019-01-07 00:00:00",
   "status": 1,
   "created_by": 1
 },
 {
   "contract_id": 218,
   "investor_id": 53,
   "date_init": "2017-08-31",
   "date_expired": "2019-08-31",
   "amount": 1000000,
   "initial_amount": 1000000,
   "created_at": "2019-01-07 00:00:00",
   "updated_at": "2019-01-07 00:00:00",
   "status": 1,
   "created_by": 1
 },
 {
   "contract_id": 218,
   "investor_id": 53,
   "date_init": "2017-11-22",
   "date_expired": "2019-02-09",
   "amount": 1000000,
   "initial_amount": 1000000,
   "created_at": "2019-01-07 00:00:00",
   "updated_at": "2019-01-07 00:00:00",
   "status": 1,
   "created_by": 1
 },
 {
   "contract_id": 218,
   "investor_id": 53,
   "date_init": "2018-02-09",
   "date_expired": "2019-02-09",
   "amount": 1000000,
   "initial_amount": 1000000,
   "created_at": "2019-01-07 00:00:00",
   "updated_at": "2019-01-07 00:00:00",
   "status": 1,
   "created_by": 1
 },
 {
   "contract_id": 218,
   "investor_id": 53,
   "date_init": "2018-05-10",
   "date_expired": "2019-05-10",
   "amount": 3000000,
   "initial_amount": 3000000,
   "created_at": "2019-01-07 00:00:00",
   "updated_at": "2019-01-07 00:00:00",
   "status": 1,
   "created_by": 1
 },
 {
   "contract_id": 219,
   "investor_id": 55,
   "date_init": "2018-10-26",
   "date_expired": "2019-10-26",
   "amount": 400000,
   "initial_amount": 400000,
   "created_at": "2019-01-07 00:00:00",
   "updated_at": "2019-01-07 00:00:00",
   "status": 1,
   "created_by": 1
 },
 {
   "contract_id": 219,
   "investor_id": 55,
   "date_init": "2018-03-02",
   "date_expired": "2019-03-02",
   "amount": 400000,
   "initial_amount": 400000,
   "created_at": "2019-01-07 00:00:00",
   "updated_at": "2019-01-07 00:00:00",
   "status": 1,
   "created_by": 1
 },
 {
   "contract_id": 219,
   "investor_id": 55,
   "date_init": "2018-02-15",
   "date_expired": "2019-02-15",
   "amount": 1320000,
   "initial_amount": 1320000,
   "created_at": "2019-01-07 00:00:00",
   "updated_at": "2019-01-07 00:00:00",
   "status": 1,
   "created_by": 1
 },
 {
   "contract_id": 219,
   "investor_id": 55,
   "date_init": "2018-04-24",
   "date_expired": "2019-04-24",
   "amount": 1280000,
   "initial_amount": 1280000,
   "created_at": "2019-01-07 00:00:00",
   "updated_at": "2019-01-07 00:00:00",
   "status": 1,
   "created_by": 1
 },
 {
   "contract_id": 220,
   "investor_id": 57,
   "date_init": "2018-02-28",
   "date_expired": "2019-02-28",
   "amount": 2000000,
   "initial_amount": 2000000,
   "created_at": "2019-01-07 00:00:00",
   "updated_at": "2019-01-07 00:00:00",
   "status": 1,
   "created_by": 1
 },
 {
   "contract_id": 221,
   "investor_id": 58,
   "date_init": "2018-04-01",
   "date_expired": "2019-04-01",
   "amount": 1690000,
   "initial_amount": 1690000,
   "created_at": "2019-01-07 00:00:00",
   "updated_at": "2019-01-07 00:00:00",
   "status": 1,
   "created_by": 1
 },
 {
   "contract_id": 222,
   "investor_id": 64,
   "date_init": "2018-04-28",
   "date_expired": "2019-04-28",
   "amount": 2500000,
   "initial_amount": 2500000,
   "created_at": "2019-01-07 00:00:00",
   "updated_at": "2019-01-07 00:00:00",
   "status": 1,
   "created_by": 1
 },
 {
   "contract_id": 223,
   "investor_id": 172,
   "date_init": "2018-01-23",
   "date_expired": "2019-01-23",
   "amount": 1350000,
   "initial_amount": 1350000,
   "created_at": "2019-01-07 00:00:00",
   "updated_at": "2019-01-07 00:00:00",
   "status": 1,
   "created_by": 1
 },
 {
   "contract_id": 223,
   "investor_id": 172,
   "date_init": "2018-01-31",
   "date_expired": "2019-01-31",
   "amount": 1320307.87,
   "initial_amount": 1320307.87,
   "created_at": "2019-01-07 00:00:00",
   "updated_at": "2019-01-07 00:00:00",
   "status": 1,
   "created_by": 1
 },
 {
   "contract_id": 223,
   "investor_id": 172,
   "date_init": "2018-08-01",
   "date_expired": "2019-08-01",
   "amount": 1036611.72,
   "initial_amount": 1036611.72,
   "created_at": "2019-01-07 00:00:00",
   "updated_at": "2019-01-07 00:00:00",
   "status": 1,
   "created_by": 1
 },
 {
   "contract_id": 223,
   "investor_id": 172,
   "date_init": "2018-05-17",
   "date_expired": "2019-05-17",
   "amount": 1143080,
   "initial_amount": 1143080,
   "created_at": "2019-01-07 00:00:00",
   "updated_at": "2019-01-07 00:00:00",
   "status": 1,
   "created_by": 1
 },
 {
   "contract_id": 224,
   "investor_id": 71,
   "date_init": "2018-07-01",
   "date_expired": "2019-07-01",
   "amount": 1000000,
   "initial_amount": 1000000,
   "created_at": "2019-01-07 00:00:00",
   "updated_at": "2019-01-07 00:00:00",
   "status": 1,
   "created_by": 1
 },
 {
   "contract_id": 224,
   "investor_id": 71,
   "date_init": "2018-01-08",
   "date_expired": "2019-01-07 00:00:00",
   "amount": 1000000,
   "initial_amount": 1000000,
   "created_at": "2019-01-07 00:00:00",
   "updated_at": "2019-01-07 00:00:00",
   "status": 1,
   "created_by": 1
 },
 {
   "contract_id": 224,
   "investor_id": 71,
   "date_init": "2018-10-01",
   "date_expired": "2019-10-01",
   "amount": 1000000,
   "initial_amount": 1000000,
   "created_at": "2019-01-07 00:00:00",
   "updated_at": "2019-01-07 00:00:00",
   "status": 1,
   "created_by": 1
 },
 {
   "contract_id": 225,
   "investor_id": 173,
   "date_init": "2018-03-03",
   "date_expired": "2019-03-03",
   "amount": 800000,
   "initial_amount": 800000,
   "created_at": "2019-01-07 00:00:00",
   "updated_at": "2019-01-07 00:00:00",
   "status": 1,
   "created_by": 1
 },
 {
   "contract_id": 226,
   "investor_id": 77,
   "date_init": "2018-01-13",
   "date_expired": "2019-01-13",
   "amount": 2000000,
   "initial_amount": 2000000,
   "created_at": "2019-01-07 00:00:00",
   "updated_at": "2019-01-07 00:00:00",
   "status": 1,
   "created_by": 1
 },
 {
   "contract_id": 227,
   "investor_id": 43,
   "date_init": "2018-12-23",
   "date_expired": "2019-12-23",
   "amount": 5000000,
   "initial_amount": 5000000,
   "created_at": "2019-01-07 00:00:00",
   "updated_at": "2019-01-07 00:00:00",
   "status": 1,
   "created_by": 1
 },
 {
   "contract_id": 228,
   "investor_id": 79,
   "date_init": "2018-02-08",
   "date_expired": "2019-02-08",
   "amount": 500000,
   "initial_amount": 500000,
   "created_at": "2019-01-07 00:00:00",
   "updated_at": "2019-01-07 00:00:00",
   "status": 1,
   "created_by": 1
 },
 {
   "contract_id": 228,
   "investor_id": 79,
   "date_init": "2018-03-01",
   "date_expired": "2019-03-01",
   "amount": 500000,
   "initial_amount": 500000,
   "created_at": "2019-01-07 00:00:00",
   "updated_at": "2019-01-07 00:00:00",
   "status": 1,
   "created_by": 1
 },
 {
   "contract_id": 229,
   "investor_id": 81,
   "date_init": "2018-07-03",
   "date_expired": "2019-07-03",
   "amount": 700000,
   "initial_amount": 700000,
   "created_at": "2019-01-07 00:00:00",
   "updated_at": "2019-01-07 00:00:00",
   "status": 1,
   "created_by": 1
 },
 {
   "contract_id": 229,
   "investor_id": 81,
   "date_init": "2018-09-27",
   "date_expired": "2019-09-27",
   "amount": 700000,
   "initial_amount": 700000,
   "created_at": "2019-01-07 00:00:00",
   "updated_at": "2019-01-07 00:00:00",
   "status": 1,
   "created_by": 1
 },
 {
   "contract_id": 229,
   "investor_id": 81,
   "date_init": "2018-02-28",
   "date_expired": "2019-02-28",
   "amount": 1000000,
   "initial_amount": 1000000,
   "created_at": "2019-01-07 00:00:00",
   "updated_at": "2019-01-07 00:00:00",
   "status": 1,
   "created_by": 1
 },
 {
   "contract_id": 229,
   "investor_id": 81,
   "date_init": "2018-11-01",
   "date_expired": "2019-11-01",
   "amount": 500000,
   "initial_amount": 500000,
   "created_at": "2019-01-07 00:00:00",
   "updated_at": "2019-01-07 00:00:00",
   "status": 1,
   "created_by": 1
 },
 {
   "contract_id": 229,
   "investor_id": 81,
   "date_init": "2018-11-06",
   "date_expired": "2019-11-06",
   "amount": 700000,
   "initial_amount": 700000,
   "created_at": "2019-01-07 00:00:00",
   "updated_at": "2019-01-07 00:00:00",
   "status": 1,
   "created_by": 1
 },
 {
   "contract_id": 230,
   "investor_id": 84,
   "date_init": "2018-05-31",
   "date_expired": "2019-05-31",
   "amount": 728224,
   "initial_amount": 728224,
   "created_at": "2019-01-07 00:00:00",
   "updated_at": "2019-01-07 00:00:00",
   "status": 1,
   "created_by": 1
 },
 {
   "contract_id": 171,
   "investor_id": 85,
   "date_init": "2018-03-30",
   "date_expired": "2019-03-30",
   "amount": 1000000,
   "initial_amount": 1000000,
   "created_at": "2019-01-07 00:00:00",
   "updated_at": "2019-01-07 00:00:00",
   "status": 1,
   "created_by": 1
 },
 {
   "contract_id": 172,
   "investor_id": 92,
   "date_init": "2018-04-26",
   "date_expired": "2019-04-26",
   "amount": 3000000,
   "initial_amount": 3000000,
   "created_at": "2019-01-07 00:00:00",
   "updated_at": "2019-01-07 00:00:00",
   "status": 1,
   "created_by": 1
 },
 {
   "contract_id": 231,
   "investor_id": 51,
   "date_init": "2018-03-01",
   "date_expired": "2019-03-01",
   "amount": 500000,
   "initial_amount": 500000,
   "created_at": "2019-01-07 00:00:00",
   "updated_at": "2019-01-07 00:00:00",
   "status": 1,
   "created_by": 1
 },
 {
   "contract_id": 231,
   "investor_id": 51,
   "date_init": "2018-06-07",
   "date_expired": "2019-06-07",
   "amount": 1100000,
   "initial_amount": 1100000,
   "created_at": "2019-01-07 00:00:00",
   "updated_at": "2019-01-07 00:00:00",
   "status": 1,
   "created_by": 1
 },
 {
   "contract_id": 232,
   "investor_id": 171,
   "date_init": "2018-01-21",
   "date_expired": "2019-01-21",
   "amount": 2040135,
   "initial_amount": 2040135,
   "created_at": "2019-01-07 00:00:00",
   "updated_at": "2019-01-07 00:00:00",
   "status": 1,
   "created_by": 1
 },
 {
   "contract_id": 232,
   "investor_id": 171,
   "date_init": "2018-11-22",
   "date_expired": "2019-07-24",
   "amount": 750000,
   "initial_amount": 750000,
   "created_at": "2019-01-07 00:00:00",
   "updated_at": "2019-01-07 00:00:00",
   "status": 1,
   "created_by": 1
 },
 {
   "contract_id": 233,
   "investor_id": 100,
   "date_init": "2018-09-01",
   "date_expired": "2019-09-01",
   "amount": 1000000,
   "initial_amount": 1000000,
   "created_at": "2019-01-07 00:00:00",
   "updated_at": "2019-01-07 00:00:00",
   "status": 1,
   "created_by": 1
 },
 {
   "contract_id": 233,
   "investor_id": 100,
   "date_init": "2018-02-14",
   "date_expired": "2019-02-14",
   "amount": 400000,
   "initial_amount": 400000,
   "created_at": "2019-01-07 00:00:00",
   "updated_at": "2019-01-07 00:00:00",
   "status": 1,
   "created_by": 1
 },
 {
   "contract_id": 233,
   "investor_id": 100,
   "date_init": "2018-10-12",
   "date_expired": "2019-10-12",
   "amount": 431986,
   "initial_amount": 431986,
   "created_at": "2019-01-07 00:00:00",
   "updated_at": "2019-01-07 00:00:00",
   "status": 1,
   "created_by": 1
 },
 {
   "contract_id": 233,
   "investor_id": 100,
   "date_init": "2018-10-16",
   "date_expired": "2019-10-16",
   "amount": 144014,
   "initial_amount": 144014,
   "created_at": "2019-01-07 00:00:00",
   "updated_at": "2019-01-07 00:00:00",
   "status": 1,
   "created_by": 1
 },
 {
   "contract_id": 234,
   "investor_id": 103,
   "date_init": "2018-09-25",
   "date_expired": "2019-09-25",
   "amount": 300000,
   "initial_amount": 300000,
   "created_at": "2019-01-07 00:00:00",
   "updated_at": "2019-01-07 00:00:00",
   "status": 1,
   "created_by": 1
 },
 {
   "contract_id": 235,
   "investor_id": 105,
   "date_init": "2018-10-13",
   "date_expired": "2019-10-13",
   "amount": 1000015,
   "initial_amount": 1000015,
   "created_at": "2019-01-07 00:00:00",
   "updated_at": "2019-01-07 00:00:00",
   "status": 1,
   "created_by": 1
 },
 {
   "contract_id": 236,
   "investor_id": 106,
   "date_init": "2018-10-27",
   "date_expired": "2019-10-27",
   "amount": 1000000,
   "initial_amount": 1000000,
   "created_at": "2019-01-07 00:00:00",
   "updated_at": "2019-01-07 00:00:00",
   "status": 1,
   "created_by": 1
 },
 {
   "contract_id": 237,
   "investor_id": 197,
   "date_init": "2018-11-07",
   "date_expired": "2019-11-07",
   "amount": 1197708,
   "initial_amount": 1197708,
   "created_at": "2019-01-07 00:00:00",
   "updated_at": "2019-01-07 00:00:00",
   "status": 1,
   "created_by": 1
 },
 {
   "contract_id": 238,
   "investor_id": 111,
   "date_init": "2018-01-05",
   "date_expired": "2019-01-05",
   "amount": 1500000,
   "initial_amount": 1500000,
   "created_at": "2019-01-07 00:00:00",
   "updated_at": "2019-01-07 00:00:00",
   "status": 1,
   "created_by": 1
 },
 {
   "contract_id": 1,
   "investor_id": 1,
   "date_init": "2018-01-15",
   "date_expired": "2019-01-15",
   "amount": 6000000,
   "initial_amount": 6000000,
   "created_at": "2019-01-07 00:00:00",
   "updated_at": "2019-01-07 00:00:00",
   "status": 1,
   "created_by": 1
 },
 {
   "contract_id": 239,
   "investor_id": 113,
   "date_init": "2018-01-15",
   "date_expired": "2019-01-15",
   "amount": 2500000,
   "initial_amount": 2500000,
   "created_at": "2019-01-07 00:00:00",
   "updated_at": "2019-01-07 00:00:00",
   "status": 1,
   "created_by": 1
 },
 {
   "contract_id": 239,
   "investor_id": 113,
   "date_init": "2018-07-04",
   "date_expired": "2019-07-04",
   "amount": 5000000,
   "initial_amount": 5000000,
   "created_at": "2019-01-07 00:00:00",
   "updated_at": "2019-01-07 00:00:00",
   "status": 1,
   "created_by": 1
 },
 {
   "contract_id": 240,
   "investor_id": 197,
   "date_init": "2018-01-16",
   "date_expired": "2019-01-16",
   "amount": 1000000,
   "initial_amount": 1000000,
   "created_at": "2019-01-07 00:00:00",
   "updated_at": "2019-01-07 00:00:00",
   "status": 1,
   "created_by": 1
 },
 {
   "contract_id": 241,
   "investor_id": 176,
   "date_init": "2018-04-27",
   "date_expired": "2019-04-27",
   "amount": 1000000,
   "initial_amount": 1000000,
   "created_at": "2019-01-07 00:00:00",
   "updated_at": "2019-01-07 00:00:00",
   "status": 1,
   "created_by": 1
 },
 {
   "contract_id": 242,
   "investor_id": 128,
   "date_init": "2018-05-07",
   "date_expired": "2019-05-07",
   "amount": 1000000,
   "initial_amount": 1000000,
   "created_at": "2019-01-07 00:00:00",
   "updated_at": "2019-01-07 00:00:00",
   "status": 1,
   "created_by": 1
 },
 {
   "contract_id": 242,
   "investor_id": 128,
   "date_init": "2018-07-30",
   "date_expired": "2019-07-30",
   "amount": 600000,
   "initial_amount": 600000,
   "created_at": "2019-01-07 00:00:00",
   "updated_at": "2019-01-07 00:00:00",
   "status": 1,
   "created_by": 1
 },
 {
   "contract_id": 243,
   "investor_id": 131,
   "date_init": "2018-05-18",
   "date_expired": "2019-05-18",
   "amount": 1170000,
   "initial_amount": 1170000,
   "created_at": "2019-01-07 00:00:00",
   "updated_at": "2019-01-07 00:00:00",
   "status": 1,
   "created_by": 1
 },
 {
   "contract_id": 170,
   "investor_id": 174,
   "date_init": "2018-11-01",
   "date_expired": "2019-11-01",
   "amount": 6750000,
   "initial_amount": 6750000,
   "created_at": "2019-01-07 00:00:00",
   "updated_at": "2019-01-07 00:00:00",
   "status": 1,
   "created_by": 1
 },
 {
   "contract_id": 170,
   "investor_id": 174,
   "date_init": "2018-05-01",
   "date_expired": "2019-05-01",
   "amount": 6750000,
   "initial_amount": 6750000,
   "created_at": "2019-01-07 00:00:00",
   "updated_at": "2019-01-07 00:00:00",
   "status": 1,
   "created_by": 1
 },
 {
   "contract_id": 244,
   "investor_id": 175,
   "date_init": "2018-07-06",
   "date_expired": "2019-07-06",
   "amount": 670000,
   "initial_amount": 670000,
   "created_at": "2019-01-07 00:00:00",
   "updated_at": "2019-01-07 00:00:00",
   "status": 1,
   "created_by": 1
 },
 {
   "contract_id": 245,
   "investor_id": 176,
   "date_init": "2018-08-20",
   "date_expired": "2019-08-20",
   "amount": 1000000,
   "initial_amount": 1000000,
   "created_at": "2019-01-07 00:00:00",
   "updated_at": "2019-01-07 00:00:00",
   "status": 1,
   "created_by": 1
 },
 {
   "contract_id": 173,
   "investor_id": 144,
   "date_init": "2018-08-31",
   "date_expired": "2019-08-31",
   "amount": 1850000,
   "initial_amount": 1850000,
   "created_at": "2019-01-07 00:00:00",
   "updated_at": "2019-01-07 00:00:00",
   "status": 1,
   "created_by": 1
 },
 {
   "contract_id": 246,
   "investor_id": 177,
   "date_init": "2018-09-04",
   "date_expired": "2019-09-04",
   "amount": 3000000,
   "initial_amount": 3000000,
   "created_at": "2019-01-07 00:00:00",
   "updated_at": "2019-01-07 00:00:00",
   "status": 1,
   "created_by": 1
 },
 {
   "contract_id": 247,
   "investor_id": 178,
   "date_init": "2018-11-03",
   "date_expired": "2019-11-03",
   "amount": 500000,
   "initial_amount": 500000,
   "created_at": "2019-01-07 00:00:00",
   "updated_at": "2019-01-07 00:00:00",
   "status": 1,
   "created_by": 1
 },
 {
   "contract_id": 247,
   "investor_id": 178,
   "date_init": "2018-12-01",
   "date_expired": "2019-12-01",
   "amount": 500000,
   "initial_amount": 500000,
   "created_at": "2019-01-07 00:00:00",
   "updated_at": "2019-01-07 00:00:00",
   "status": 1,
   "created_by": 1
 },
 {
   "contract_id": 247,
   "investor_id": 178,
   "date_init": "2018-05-15",
   "date_expired": "2019-05-15",
   "amount": 500000,
   "initial_amount": 500000,
   "created_at": "2019-01-07 00:00:00",
   "updated_at": "2019-01-07 00:00:00",
   "status": 1,
   "created_by": 1
 },
 {
   "contract_id": 248,
   "investor_id": 178,
   "date_init": "2018-08-31",
   "date_expired": "2019-08-31",
   "amount": 300000,
   "initial_amount": 300000,
   "created_at": "2019-01-07 00:00:00",
   "updated_at": "2019-01-07 00:00:00",
   "status": 1,
   "created_by": 1
 },
 {
   "contract_id": 249,
   "investor_id": 174,
   "date_init": "2018-05-24",
   "date_expired": "2019-05-24",
   "amount": 1000000,
   "initial_amount": 1000000,
   "created_at": "2019-01-07 00:00:00",
   "updated_at": "2019-01-07 00:00:00",
   "status": 1,
   "created_by": 1
 },
 {
   "contract_id": 250,
   "investor_id": 13,
   "date_init": "2018-11-14",
   "date_expired": "2019-11-14",
   "amount": 788400,
   "initial_amount": 788400,
   "created_at": "2019-01-07 00:00:00",
   "updated_at": "2019-01-07 00:00:00",
   "status": 1,
   "created_by": 1
 },
 {
   "contract_id": 252,
   "investor_id": 190,
   "date_init": "2018-11-27",
   "date_expired": "2019-11-27",
   "amount": 1500000,
   "initial_amount": 1500000,
   "created_at": "2019-01-07 00:00:00",
   "updated_at": "2019-01-07 00:00:00",
   "status": 1,
   "created_by": 1
 },
 {
   "contract_id": 252,
   "investor_id": 190,
   "date_init": "2018-12-13",
   "date_expired": "2019-12-13",
   "amount": 500000,
   "initial_amount": 500000,
   "created_at": "2019-01-07 00:00:00",
   "updated_at": "2019-01-07 00:00:00",
   "status": 1,
   "created_by": 1
 },
 {
   "contract_id": 253,
   "investor_id": 191,
   "date_init": "2018-12-20",
   "date_expired": "2018-12-20",
   "amount": 2050000,
   "initial_amount": 2050000,
   "created_at": "2019-01-07 00:00:00",
   "updated_at": "2019-01-07 00:00:00",
   "status": 1,
   "created_by": 1
 }
]